pexpect/ANSI.py
pexpect/FSM.py
pexpect/__init__.py
pexpect/_async.py
pexpect/bashrc.sh
pexpect/exceptions.py
pexpect/expect.py
pexpect/fdpexpect.py
pexpect/popen_spawn.py
pexpect/pty_spawn.py
pexpect/pxssh.py
pexpect/replwrap.py
pexpect/run.py
pexpect/screen.py
pexpect/spawnbase.py
pexpect/utils.py
pexpect-4.3.0.dist-info/DESCRIPTION.rst
pexpect-4.3.0.dist-info/METADATA
pexpect-4.3.0.dist-info/RECORD
pexpect-4.3.0.dist-info/WHEEL
pexpect-4.3.0.dist-info/metadata.json
pexpect-4.3.0.dist-info/top_level.txt
